[{"img":"cms-data\/gallery\/blog\/mindtickler\/doership-and-responsibility\/image.jpg","alt":"","date":1624377496,"featured":false,"exif":{"focalLength":"","aperture":"","exposureBias":"","shutterSpeed":"","iso":"","date":"","make":"","model":"","copyright":"","caption":"","title":"","width":541,"height":148},"link":"","filename":"image","thumb":{"th":"cms-data\/gallery\/blog\/mindtickler\/doership-and-responsibility\/image-th.jpg","sq":"cms-data\/gallery\/blog\/mindtickler\/doership-and-responsibility\/image-sq.jpg"}}]